richery/__init__.py
richery/ansitool.py
richery/canvas.py
richery/colordef.py
richery/textwork.py
richery-0.1.1.dist-info/LICENSE
richery-0.1.1.dist-info/METADATA
richery-0.1.1.dist-info/WHEEL
richery-0.1.1.dist-info/top_level.txt
richery-0.1.1.dist-info/RECORD
