Metadata-Version: 2.1
Name: richery
Version: 0.1.1
Summary: Supercharged rich text renderer based on Pillow
Author-email: HivertMoZara <worldmozara@163.com>
License: MIT
Project-URL: Homepage, https://github.com/NCBM/richery-pil
Project-URL: Repository, https://github.com/NCBM/richery-pil
Requires-Python: >=3.8
License-File: LICENSE
Requires-Dist: Pillow (>=9.4)
